{
	// "modules":[
	// 	{
	// 		"npm": "lightning/dualListbox"
	// 	}
	// ],
		"assets": [
			{
					"alias": "assetsDir",
					"dir": "$rootDir/src/assets",
					"urlPath": "/assets"
			},
			{
					"dir": "$rootDir/src/assets/fonts",
					"urlPath": "/fonts"
			},
			{
					"file": "$rootDir/src/assets/utilitySprite.svg",
					"urlPath": "/lightning.utilitySprite"
			}
	],
    "routes": [
			{
				"id": "my-app",
				"path": "/",
				"rootComponent": "tnf/list",
				"layoutTemplate": "$layoutsDir/main.html",
				"bootstrap": {
						"syntheticShadow": true
				}
		}
    ]
}
